lithophane/__init__.py
lithophane/__main__.py
lithophane/metadata.py
lithophane-1.0.8.dist-info/LICENSE
lithophane-1.0.8.dist-info/METADATA
lithophane-1.0.8.dist-info/WHEEL
lithophane-1.0.8.dist-info/top_level.txt
lithophane-1.0.8.dist-info/RECORD
