Metadata-Version: 2.1
Name: lithophane
Version: 1.0.8
Summary: This module generates a 3D model of a lithophane from an given image.
Home-page: https://github.com/robbyHuelsi/lithophane
Download-URL: https://github.com/robbyHuelsi/lithophane/archive/v_1.0.8.tar.gz
Author: Dirk Colbry
Author-email: robby@huelsi.de
License: MIT
Keywords: lithophane,stl,3d-printing,3d,image,translucent
Classifier: Development Status :: 5 - Production/Stable
Classifier: Intended Audience :: Developers
Classifier: Topic :: Software Development :: Build Tools
Classifier: License :: OSI Approved :: MIT License
Classifier: Programming Language :: Python :: 3.8
Classifier: Programming Language :: Python :: 3.9
Classifier: Programming Language :: Python :: 3.10
Classifier: Programming Language :: Python :: 3.11
Classifier: Programming Language :: Python :: 3.12
Requires-Python: >=3.8
License-File: LICENSE
Requires-Dist: matplotlib
Requires-Dist: numpy
Requires-Dist: numpy-stl
Requires-Dist: scikit-image
